causal_inference/__init__.py
causal_inference/config.py
causal_inference/base/__init__.py
causal_inference/base/lotka_volterra.py
causal_inference/tests/__init__.py
causal_inference/tests/test_lv_simulator.py
causal_inference/utils/__init__.py
causal_inference/utils/log_config.py
causal_inference_population_dynamics-1.0.2.dist-info/LICENSE
causal_inference_population_dynamics-1.0.2.dist-info/METADATA
causal_inference_population_dynamics-1.0.2.dist-info/WHEEL
causal_inference_population_dynamics-1.0.2.dist-info/top_level.txt
causal_inference_population_dynamics-1.0.2.dist-info/RECORD
