Metadata-Version: 2.1
Name: causal-inference-population-dynamics
Version: 1.0.2
Summary: Library to conduct experiments in population dynamics.
Home-page: https://github.com/artificial-life-lab/population-dynamics
Author: Pranjal Dhole
Author-email: dhole.pranjal@gmail.com
License: MIT
Platform: UNKNOWN
Classifier: Programming Language :: Python :: 3
Classifier: Programming Language :: Python :: 3.7
Classifier: Programming Language :: Python :: 3.8
Classifier: Programming Language :: Python :: 3.9
Requires-Python: >=3.7
License-File: LICENSE
Requires-Dist: numpy
Requires-Dist: h5py
Requires-Dist: matplotlib
